bafser_tgapi/__init__.py
bafser_tgapi/bot.py
bafser_tgapi/bot_with_db.py
bafser_tgapi/helpers.py
bafser_tgapi/methods.py
bafser_tgapi/types.py
bafser_tgapi/utils.py
bafser_tgapi/db/msg.py
bafser_tgapi/db/user.py
bafser_tgapi/tools/stickers.html
bafser_tgapi/tools/stickers.py
bafser_tgapi-1.7.1.dist-info/METADATA
bafser_tgapi-1.7.1.dist-info/WHEEL
bafser_tgapi-1.7.1.dist-info/licenses/LICENSE
bafser_tgapi-1.7.1.dist-info/RECORD
