Metadata-Version: 2.4
Name: bafser_tgapi
Version: 1.7.1
Summary: bafser tg api
Project-URL: Homepage, https://github.com/MixelTe/bafser_tgapi
Project-URL: Issues, https://github.com/MixelTe/bafser_tgapi/issues
Author: Mixel Te
License-Expression: MIT
License-File: LICENSE
Classifier: Operating System :: OS Independent
Classifier: Programming Language :: Python :: 3.12
Requires-Python: >=3.12
Requires-Dist: bafser~=2.5.2
Requires-Dist: requests
